{"expires": 1766435014, "value": "{\"cagr_1y\": 8.5, \"cagr_2y\": 9.2, \"cagr_5y\": 10.1, \"cagr_10y\": 8.8, \"reasoning\": \"Based on the provided financial data, considering the sector, beta, and valuation metrics, a conservative estimate is made. The high current P/E ratio may indicate potential for correction, while the lower forward P/E suggests expected growth. The ROE is relatively low, which might impact long-term returns. Given these factors, the predicted CAGRs are set, assuming market and economic conditions remain stable.\"}"}